gravity_controller_operator/__init__.py
gravity_controller_operator/controller_factory.py
gravity_controller_operator/controllers_super.py
gravity_controller_operator/exceptions.py
gravity_controller_operator/main.py
gravity_controller_operator/controllers/__init__.py
gravity_controller_operator/controllers/arm_k210.py
gravity_controller_operator/controllers/emulator_contr.py
gravity_controller_operator/controllers/moxa.py
gravity_controller_operator/controllers/netping_relay.py
gravity_controller_operator/controllers/sigur.py
gravity_controller_operator/controllers/wb_mr6lv.py
gravity_controller_operator/controllers/tests/__init__.py
gravity_controller_operator/controllers/tests/test_moxa_controller.py
gravity_controller_operator/docs/__init__.py
gravity_controller_operator/tests/__init__.py
gravity_controller_operator/tests/main_tests.py
gravity_controller_operator-2.2.5.dist-info/licenses/LICENSE
gravity_controller_operator-2.2.5.dist-info/METADATA
gravity_controller_operator-2.2.5.dist-info/WHEEL
gravity_controller_operator-2.2.5.dist-info/top_level.txt
gravity_controller_operator-2.2.5.dist-info/RECORD
