Metadata-Version: 2.4
Name: gravity_controller_operator
Version: 2.2.5
Summary: SDK предоставляющий универсальный интерфейс для работы со многими промышленными контроллерами ввода-вывода (количество расширяемо)
Author: PunchyArchy
Author-email: ksmdrmvscthny@gmail.com
Classifier: Programming Language :: Python :: 3
Classifier: Operating System :: OS Independent
Requires-Python: >=3.7
License-File: LICENSE
Requires-Dist: pyModbusTCP
Requires-Dist: pymodbus==3.6.9
Dynamic: author
Dynamic: author-email
Dynamic: classifier
Dynamic: description
Dynamic: description-content-type
Dynamic: license-file
Dynamic: requires-dist
Dynamic: requires-python
Dynamic: summary
